<annotation>
	<folder>tflight_images</folder>
	<filename>0236.jpg</filename>
	<path>/home/rikki/Desktop/tflight_images/0236.jpg</path>
	<source>
		<database>Unknown</database>
	</source>
	<size>
		<width>800</width>
		<height>600</height>
		<depth>3</depth>
	</size>
	<segmented>0</segmented>
	<object>
		<name>red</name>
		<pose>Unspecified</pose>
		<truncated>0</truncated>
		<difficult>0</difficult>
		<bndbox>
			<xmin>48</xmin>
			<ymin>239</ymin>
			<xmax>114</xmax>
			<ymax>376</ymax>
		</bndbox>
	</object>
	<object>
		<name>red</name>
		<pose>Unspecified</pose>
		<truncated>0</truncated>
		<difficult>0</difficult>
		<bndbox>
			<xmin>580</xmin>
			<ymin>264</ymin>
			<xmax>646</xmax>
			<ymax>401</ymax>
		</bndbox>
	</object>
	<object>
		<name>red</name>
		<pose>Unspecified</pose>
		<truncated>0</truncated>
		<difficult>0</difficult>
		<bndbox>
			<xmin>318</xmin>
			<ymin>252</ymin>
			<xmax>384</xmax>
			<ymax>389</ymax>
		</bndbox>
	</object>
</annotation>
